dayoffs/__init__.py
dayoffs/holiday_manager.py
dayoffs/holidays/__init__.py
dayoffs/locales/__init__.py
dayoffs/utils/__init__.py
dayoffs/utils/date_utils.py
tests/__init__.py
tests/test_holiday_manager.py
tests/holidays/__init__.py
tests/locales/__init__.py
tests/utils/__init__.py
tests/utils/test_date_utils.py
dayoffs-0.0.1.dist-info/LICENSE
dayoffs-0.0.1.dist-info/METADATA
dayoffs-0.0.1.dist-info/WHEEL
dayoffs-0.0.1.dist-info/top_level.txt
dayoffs-0.0.1.dist-info/RECORD
