Metadata-Version: 2.1
Name: dayoffs
Version: 0.0.1
Summary: A Python library for managing holidays and days off.
Home-page: https://github.com/r4mbhardwaj/dayoffs
Author: Ram Bhardwaj
Author-email: r4mbhardwaj@gmail.com
Classifier: Programming Language :: Python :: 3
Classifier: License :: OSI Approved :: MIT License
Classifier: Operating System :: OS Independent
Requires-Python: >=3.6
License-File: LICENSE
